gauge/__init__.py
gauge/gauge.py
gauge_llm-0.0.121.dist-info/LICENSE
gauge_llm-0.0.121.dist-info/METADATA
gauge_llm-0.0.121.dist-info/WHEEL
gauge_llm-0.0.121.dist-info/RECORD
